truckle/__init__.py
truckle/truckle.py
truckle-0.1.2.dist-info/LICENSE
truckle-0.1.2.dist-info/METADATA
truckle-0.1.2.dist-info/WHEEL
truckle-0.1.2.dist-info/top_level.txt
truckle-0.1.2.dist-info/RECORD
