Metadata-Version: 2.1
Name: truckle
Version: 0.1.2
Summary: A simple setuptools alternative for packing Python modules (with or without FFI bindings) into wheels.
Author: Wyatt Howe
Author-email: wyatt@brown.edu
License: MIT
Project-URL: Repository, https://github.com/wyatt-howe/truckle
Project-URL: Documentation, https://truckle.readthedocs.io
Requires-Python: >=3.7
License-File: LICENSE
Provides-Extra: coveralls
Requires-Dist: coveralls (~=3.3.1) ; extra == 'coveralls'
Provides-Extra: docs
Requires-Dist: toml (~=0.10.2) ; extra == 'docs'
Requires-Dist: sphinx (~=4.2.0) ; extra == 'docs'
Requires-Dist: sphinx-rtd-theme (~=1.0.0) ; extra == 'docs'
Provides-Extra: lint
Requires-Dist: pylint (~=2.14.0) ; extra == 'lint'
Provides-Extra: publish
Requires-Dist: twine (~=4.0) ; extra == 'publish'
Provides-Extra: test
Requires-Dist: pytest (~=7.0) ; extra == 'test'
Requires-Dist: pytest-cov (~=3.0) ; extra == 'test'
